boxjenkins/__init__.py
boxjenkins/models.py
boxjenkins-1.1.1.dist-info/licenses/LICENSE
boxjenkins-1.1.1.dist-info/METADATA
boxjenkins-1.1.1.dist-info/WHEEL
boxjenkins-1.1.1.dist-info/top_level.txt
boxjenkins-1.1.1.dist-info/RECORD
