Metadata-Version: 2.4
Name: boxjenkins
Version: 1.1.1
Summary: Implementação completa do ciclo Box-Jenkins para modelagem ARIMA
Home-page: https://github.com/GersonRS/boxjenkins
Author: Gerson RS
Author-email: 
License: MIT
Project-URL: Homepage, https://github.com/GersonRS/boxjenkins
Project-URL: Repository, https://github.com/GersonRS/boxjenkins
Project-URL: Bug Tracker, https://github.com/GersonRS/boxjenkins/issues
Keywords: arima,box-jenkins,time-series,forecasting,statistics
Classifier: Development Status :: 3 - Alpha
Classifier: Intended Audience :: Science/Research
Classifier: Intended Audience :: Developers
Classifier: Topic :: Scientific/Engineering :: Mathematics
Classifier: Topic :: Scientific/Engineering :: Information Analysis
Classifier: License :: OSI Approved :: MIT License
Classifier: Programming Language :: Python :: 3
Classifier: Programming Language :: Python :: 3.8
Classifier: Programming Language :: Python :: 3.9
Classifier: Programming Language :: Python :: 3.10
Classifier: Programming Language :: Python :: 3.11
Requires-Python: >=3.8
License-File: LICENSE
Requires-Dist: numpy>=1.20.0
Requires-Dist: pandas>=1.3.0
Requires-Dist: scipy>=1.7.0
Requires-Dist: matplotlib>=3.4.0
Requires-Dist: seaborn>=0.11.0
Provides-Extra: dev
Requires-Dist: pytest>=7.0; extra == "dev"
Requires-Dist: pytest-cov>=3.0; extra == "dev"
Requires-Dist: black>=22.0; extra == "dev"
Requires-Dist: flake8>=4.0; extra == "dev"
Requires-Dist: isort>=5.10; extra == "dev"
Dynamic: home-page
Dynamic: license-file
Dynamic: requires-python
